epopt/__init__.py
epopt/_solve.so
epopt/affine.py
epopt/constant.py
epopt/constant_atoms_test.py
epopt/cvxpy_expr.py
epopt/cvxpy_solver.py
epopt/dcp.py
epopt/error.py
epopt/expression.py
epopt/expression_testutil.py
epopt/expression_util.py
epopt/expression_vis.py
epopt/functions.py
epopt/functions_test.py
epopt/linear_map.py
epopt/list_format.py
epopt/prox.py
epopt/prox_test.py
epopt/solve_test.py
epopt/text_format.py
epopt/tree_format.py
epopt/util.py
epopt/compiler/__init__.py
epopt/compiler/compiler.py
epopt/compiler/compiler_test.py
epopt/compiler/problem_graph.py
epopt/compiler/validate.py
epopt/compiler/transforms/__init__.py
epopt/compiler/transforms/conic.py
epopt/compiler/transforms/linear.py
epopt/compiler/transforms/prox.py
epopt/compiler/transforms/separate.py
epopt/compiler/transforms/split.py
epopt/compiler/transforms/transform_util.py
epopt/examples/__init__.py
epopt/examples/graphs.py
epopt/problems/__init__.py
epopt/problems/baby.jpg
epopt/problems/basis_pursuit.py
epopt/problems/benchmark.py
epopt/problems/benchmark_bars.py
epopt/problems/benchmark_format.py
epopt/problems/benchmark_graph.py
epopt/problems/benchmark_specialized.py
epopt/problems/benchmark_test.py
epopt/problems/benchmark_util.py
epopt/problems/chebyshev.py
epopt/problems/covsel.py
epopt/problems/fused_lasso.py
epopt/problems/group_lasso.py
epopt/problems/hinge.py
epopt/problems/hinge_l1.py
epopt/problems/hinge_l2.py
epopt/problems/huber.py
epopt/problems/infinite_push.py
epopt/problems/lad_svm.py
epopt/problems/lasso.py
epopt/problems/least_abs_dev.py
epopt/problems/least_abs_dev_kernel.py
epopt/problems/logreg_l1.py
epopt/problems/lp.py
epopt/problems/max_gaussian.py
epopt/problems/max_softmax.py
epopt/problems/mnist.py
epopt/problems/mnist_small.mat
epopt/problems/mnist_tiny.mat
epopt/problems/oneclass_svm.py
epopt/problems/portfolio.py
epopt/problems/print.py
epopt/problems/problem_instance.py
epopt-0.2.4.dist-info/DESCRIPTION.rst
epopt-0.2.4.dist-info/METADATA
epopt-0.2.4.dist-info/RECORD
epopt-0.2.4.dist-info/WHEEL
epopt-0.2.4.dist-info/metadata.json
epopt-0.2.4.dist-info/top_level.txt
