Metadata-Version: 2.0
Name: epopt
Version: 0.2.4
Summary: UNKNOWN
Home-page: http://epopt.io/
Author: Matt Wytock
Author-email: mwytock@gmail.com
License: UNKNOWN
Platform: UNKNOWN
Requires-Dist: cvxpy (==0.3.6)
Requires-Dist: protobuf (>=3.0.0a3)
